wu/__init__.py
wu/fixExcelIndex.py
fix_something_mzw-0.0.1.dist-info/LICENSE
fix_something_mzw-0.0.1.dist-info/METADATA
fix_something_mzw-0.0.1.dist-info/WHEEL
fix_something_mzw-0.0.1.dist-info/top_level.txt
fix_something_mzw-0.0.1.dist-info/RECORD
