Metadata-Version: 2.1
Name: fix-something-mzw
Version: 0.0.1
Summary: fix java entity excel index
Author: wu
Author-email: m1045264407@163.com
Classifier: Programming Language :: Python :: 3
Classifier: Operating System :: OS Independent
License-File: LICENSE
